[
  {
    "title": "ГЪРЦИЯ - ХАЛКИДИКИ, Хотел Poseidon Hotel Sea Resort",
    "link": "https://aventura.bg/pochivka/1691/1/65/%D0%B3%D1%8A%D1%80%D1%86%D0%B8%D1%8F-%D1%85%D0%B0%D0%BB%D0%BA%D0%B8%D0%B4%D0%B8%D0%BA%D0%B8-%D1%85%D0%BE%D1%82%D0%B5%D0%BB-poseidon-hotel-sea-resort.html",
    "price": "69.00 EUR",
    "dates": "12.05.2026 - 01.10.2026",
    "destination": "Гърция",
    "scraped_at": "2025-10-25T15:27:02.591872"
  },
  {
    "title": "ГЪРЦИЯ - ХАЛКИДИКИ, Хотел Aegean Melathron Hotel Гърция - Халкидики",
    "link": "https://aventura.bg/pochivka/262/1/34/%D0%B3%D1%8A%D1%80%D1%86%D0%B8%D1%8F-%D1%85%D0%B0%D0%BB%D0%BA%D0%B8%D0%B4%D0%B8%D0%BA%D0%B8-%D1%85%D0%BE%D1%82%D0%B5%D0%BB-aegean-melathron-hotel.html",
    "price": "49.00 EUR",
    "dates": "30.04.2026 - 01.10.2026",
    "destination": "Гърция",
    "scraped_at": "2025-10-25T15:27:04.584834"
  },
  {
    "title": "ГЪРЦИЯ - ХАЛКИДИКИ, Хотел Blue Lagoon Queen Гърция - Халкидики - Ситония",
    "link": "https://aventura.bg/pochivka/1893/1/65/%D0%B3%D1%8A%D1%80%D1%86%D0%B8%D1%8F-%D1%85%D0%B0%D0%BB%D0%BA%D0%B8%D0%B4%D0%B8%D0%BA%D0%B8-%D1%85%D0%BE%D1%82%D0%B5%D0%BB-blue-lagoon-queen.html",
    "price": "105.00 EUR",
    "dates": "01.05.2026 - 01.10.2026",
    "destination": "Гърция",
    "scraped_at": "2025-10-25T15:27:03.556809"
  },
  {
    "title": "ГЪРЦИЯ - ХАЛКИДИКИ, Хотел Mitsis Alexander The Great",
    "link": "https://aventura.bg/pochivka/375/1/34/%D0%B3%D1%8A%D1%80%D1%86%D0%B8%D1%8F-%D1%85%D0%B0%D0%BB%D0%BA%D0%B8%D0%B4%D0%B8%D0%BA%D0%B8-%D1%85%D0%BE%D1%82%D0%B5%D0%BB-mitsis-alexander-the-great.html",
    "price": "54.00 EUR",
    "dates": "01.05.2026 - 01.10.2026",
    "destination": "Гърция",
    "scraped_at": "2025-10-25T15:27:02.221060"
  },
  {
    "title": "ГЪРЦИЯ - ОСТРОВ КОРФУ, Хотел Mitsis Messonghi Гърция - Остров Корфу",
    "link": "https://aventura.bg/pochivka/613/1/67/%D0%B3%D1%8A%D1%80%D1%86%D0%B8%D1%8F-%D0%BE%D1%81%D1%82%D1%80%D0%BE%D0%B2-%D0%BA%D0%BE%D1%80%D1%84%D1%83-%D1%85%D0%BE%D1%82%D0%B5%D0%BB-mitsis-messonghi.html",
    "price": "54.00 EUR",
    "dates": "01.05.2026 - 01.10.2026",
    "destination": "Гърция",
    "scraped_at": "2025-10-25T15:27:03.082000"
  },
  {
    "title": "ГЪРЦИЯ – ХАЛКИДИКИ, Хотел Blue Dolphin Гърция - Халкидики - Ситония",
    "link": "https://aventura.bg/pochivka/326/1/65/%D0%B3%D1%8A%D1%80%D1%86%D0%B8%D1%8F-%D1%85%D0%B0%D0%BB%D0%BA%D0%B8%D0%B4%D0%B8%D0%BA%D0%B8-%D1%85%D0%BE%D1%82%D0%B5%D0%BB-blue-dolphin.html",
    "price": "39.00 EUR",
    "dates": "01.05.2026 - 01.10.2026",
    "destination": "Гърция",
    "scraped_at": "2025-10-25T15:27:01.993308"
  },
  {
    "title": "ТУНИС - СИНЬО И БЯЛО Екскурзия: 8 ДНИ Тунис 17.04.2026",
    "link": "https://aventura.bg/ekskurzia/128/8/18/%D1%82%D1%83%D0%BD%D0%B8%D1%81-%D1%81%D0%B8%D0%BD%D1%8C%D0%BE-%D0%B8-%D0%B1%D1%8F%D0%BB%D0%BE.html",
    "price": "508.00 EUR",
    "dates": "17.04.2026 - 23.10.2026",
    "destination": "Тунис",
    "scraped_at": "2025-10-25T15:27:02.841846"
  },
  {
    "title": "АНТАЛИЯ - ПЕРЛАТА НА \r\nСРЕДИЗЕМНО МОРЕ Екскурзия: 8 ДНИ Турция 03.05.2026",
    "link": "https://aventura.bg/ekskurzia/63/18/18/%D0%B0%D0%BD%D1%82%D0%B0%D0%BB%D0%B8%D1%8F-%D0%BF%D0%B5%D1%80%D0%BB%D0%B0%D1%82%D0%B0-%D0%BD%D0%B0-%D1%81%D1%80%D0%B5%D0%B4%D0%B8%D0%B7%D0%B5%D0%BC%D0%BD%D0%BE-%D0%BC%D0%BE%D1%80%D0%B5.html",
    "price": "494.00 EUR",
    "dates": "03.05.2026 - 02.10.2026",
    "destination": "Турция",
    "scraped_at": "2025-10-25T15:27:04.293315"
  },
  {
    "title": "ГЪРЦИЯ - ХАЛКИДИКИ, Хотел Potidea Palace Hotel Хотел на деня",
    "link": "https://aventura.bg/pochivka/31/1/34/%D0%B3%D1%8A%D1%80%D1%86%D0%B8%D1%8F-%D1%85%D0%B0%D0%BB%D0%BA%D0%B8%D0%B4%D0%B8%D0%BA%D0%B8-%D1%85%D0%BE%D1%82%D0%B5%D0%BB-potidea-palace-hotel.html",
    "price": "97.00 EUR",
    "dates": "29.04.2026 - 01.10.2026",
    "destination": "Гърция",
    "scraped_at": "2025-10-25T15:27:04.098436"
  },
  {
    "title": "ТУРЦИЯ - АЛАНИЯ, Хотел Q Premium Resort Турция, Анталия - Алания 03.05.2026 Това е един от по-новите хотели в курорта, който предлага отлични условия за почивка. Оригинален дизайн, в съчетание с комфортна и уютна обстановка. Отзивчив персонал, и добра анимация. Намаленията за деца са до 13 ненавършени години. ALL INCLUSIVE Free Wi-Fi На брега на морето Настаняване с 2 деца",
    "link": "https://aventura.bg/pochivka/972/18/113/%D1%82%D1%83%D1%80%D1%86%D0%B8%D1%8F-%D0%B0%D0%BB%D0%B0%D0%BD%D0%B8%D1%8F-%D1%85%D0%BE%D1%82%D0%B5%D0%BB-q-premium-resort.html",
    "price": "613.55 EUR",
    "dates": "03.05.2026 - 03.05.2026",
    "destination": "Турция",
    "scraped_at": "2025-10-25T15:27:06.590959"
  },
  {
    "title": "Дубай - Дубай Марина с 6 нощувки Екскурзия: 7 дни 31.10 - 06.11 Дубай е бляскава и модерна дестинация, която предлага съчетание от лукс, приключения и културно разнообразие. Насладете се на слънчеви плажове, сафари в пустинята, гурме кухня и атракции за цялото семейство. Идеален избор за почивка през зимата, когато времето е приятно и слънчево.",
    "link": "https://aventura.bg/ekskurzia/214/15/19/%D0%B4%D1%83%D0%B1%D0%B0%D0%B9-%D0%B4%D1%83%D0%B1%D0%B0%D0%B9-%D0%BC%D0%B0%D1%80%D0%B8%D0%BD%D0%B0-%D1%81-6-%D0%BD%D0%BE%D1%89%D1%83%D0%B2%D0%BA%D0%B8.html",
    "price": "1198.98 EUR",
    "dates": "22.03.2025 - 18.04.2026",
    "destination": "Дубай",
    "scraped_at": "2025-10-25T15:27:08.663750"
  },
  {
    "title": "БЪЛГАРИЯ - ОБЗОР, Хотел Марина Сендс България, Обзор Нов хотел в тихата част на Обзор със собствен плаж. Подходящ не само за спокойна семейна почивка с деца, но и за туристи, които искат да се отпуснат от суматохата на града. ALL INCLUSIVE Free Wi-Fi На брега на морето Препоръчан от Авентура",
    "link": "https://aventura.bg/pochivka/1710/24/37/%D0%B1%D1%8A%D0%BB%D0%B3%D0%B0%D1%80%D0%B8%D1%8F-%D0%BE%D0%B1%D0%B7%D0%BE%D1%80-%D1%85%D0%BE%D1%82%D0%B5%D0%BB-%D0%BC%D0%B0%D1%80%D0%B8%D0%BD%D0%B0-%D1%81%D0%B5%D0%BD%D0%B4%D1%81.html",
    "price": "34.26 EUR",
    "dates": "02.07.2020 - 25.08.2020",
    "destination": "Unknown",
    "scraped_at": "2025-10-25T15:27:10.421871"
  }
]